SpotiFLAC/SpotiFLAC.py
SpotiFLAC/__init__.py
SpotiFLAC/amazonDL.py
SpotiFLAC/deezerDL.py
SpotiFLAC/getMetadata.py
SpotiFLAC/qobuzDL.py
SpotiFLAC/tidalDL.py
spotiflac-0.1.6.dist-info/licenses/LICENSE
spotiflac-0.1.6.dist-info/METADATA
spotiflac-0.1.6.dist-info/WHEEL
spotiflac-0.1.6.dist-info/top_level.txt
spotiflac-0.1.6.dist-info/RECORD
