Metadata-Version: 2.4
Name: SpotiFLAC
Version: 0.1.6
Summary: Get Spotify tracks in true FLAC from Tidal, Qobuz & Amazon Music — no account required.
Author: ShuKurenais
License-Expression: MIT
Project-URL: Repository, https://github.com/ShuShuzinhuu/SpotiFLAC-Module-Version
Keywords: spotify,downloader,python,async,library,api
Requires-Python: >=3.9
License-File: LICENSE
Requires-Dist: requests~=2.32.3
Requires-Dist: mutagen~=1.47.0
Requires-Dist: pyotp~=2.9.0
Dynamic: license-file
